mseep_mcp_yfinance_server-0.1.4.dist-info/licenses/LICENSE
yfinance_mcp/__init__.py
yfinance_mcp/server.py
mseep_mcp_yfinance_server-0.1.4.dist-info/METADATA
mseep_mcp_yfinance_server-0.1.4.dist-info/WHEEL
mseep_mcp_yfinance_server-0.1.4.dist-info/entry_points.txt
mseep_mcp_yfinance_server-0.1.4.dist-info/top_level.txt
mseep_mcp_yfinance_server-0.1.4.dist-info/RECORD
