Metadata-Version: 2.4
Name: mseep-mcp-yfinance-server
Version: 0.1.4
Summary: A Yfinance MCP Server providing comprehensive financial data and analysis
Author-email: mseep <support@skydeck.ai>
Requires-Python: >=3.11
License-File: LICENSE
Requires-Dist: httpx>=0.28.1
Requires-Dist: mcp[cli]>=1.6.0
Requires-Dist: yfinance>=0.2.55
Requires-Dist: pandas>=2.0.0
Requires-Dist: numpy>=1.24.0
Requires-Dist: typing-extensions>=4.5.0
Requires-Dist: textblob>=0.19.0
Requires-Dist: matplotlib>=3.10.1
Requires-Dist: ipython>=9.1.0
Requires-Dist: fastmcp>=2.11.1
Requires-Dist: fastapi
Requires-Dist: uvicorn
Requires-Dist: plotly>=6.2.0
Dynamic: license-file
